pycounter/__init__.py
pycounter/constants.py
pycounter/csvhelper.py
pycounter/exceptions.py
pycounter/helpers.py
pycounter/report.py
pycounter/sushi.py
pycounter/sushi5.py
pycounter/sushiclient.py
pycounter/version.py
pycounter/test/__init__.py
pycounter/test/conftest.py
pycounter/test/test_bad_reports.py
pycounter/test/test_br1.py
pycounter/test/test_br2.py
pycounter/test/test_br3.py
pycounter/test/test_br_common.py
pycounter/test/test_classes.py
pycounter/test/test_db1.py
pycounter/test/test_db2.py
pycounter/test/test_db_common.py
pycounter/test/test_helpers.py
pycounter/test/test_jr1_csv.py
pycounter/test/test_jr1_tabs.py
pycounter/test/test_jr1_xslx.py
pycounter/test/test_jr2.py
pycounter/test/test_output_common.py
pycounter/test/test_output_jr1.py
pycounter/test/test_pr1.py
pycounter/test/test_sushi.py
pycounter/test/test_unicode.py
pycounter/test/counter5/__init__.py
pycounter/test/counter5/conftest.py
pycounter/test/counter5/test_output.py
pycounter/test/counter5/test_sushi.py
pycounter/test/counter5/test_trj1.py
pycounter/test/counter5/test_trj2.py
pycounter-2.1.4.dist-info/LICENSE.txt
pycounter-2.1.4.dist-info/METADATA
pycounter-2.1.4.dist-info/WHEEL
pycounter-2.1.4.dist-info/entry_points.txt
pycounter-2.1.4.dist-info/top_level.txt
pycounter-2.1.4.dist-info/RECORD
