Metadata-Version: 2.1
Name: pycounter
Version: 2.1.4
Summary: Project COUNTER/NISO SUSHI statistics
Home-page: http://www.github.com/pitthsls/pycounter
Author: Health Sciences Library System, University of Pittsburgh
Author-email: speargh@pitt.edu
Maintainer: Geoffrey Spear
Maintainer-email: speargh@pitt.edu
License: UNKNOWN
Project-URL: Documentation, https://pycounter.readthedocs.io
Keywords: library COUNTER journals usage_statistics SUSHI
Platform: UNKNOWN
Classifier: Development Status :: 5 - Production/Stable
Classifier: License :: OSI Approved :: MIT License
Classifier: Intended Audience :: Developers
Classifier: Programming Language :: Python :: 2.7
Classifier: Programming Language :: Python :: 3.5
Classifier: Programming Language :: Python :: 3.6
Classifier: Programming Language :: Python :: 3.7
Classifier: Programming Language :: Python :: 3.8
Classifier: Programming Language :: Python :: Implementation :: PyPy
Requires-Python: >=2.7, !=3.0.*, !=3.1.*, !=3.2.*, !=3.3.*, !=3.4.*
Requires-Dist: openpyxl
Requires-Dist: requests
Requires-Dist: six
Requires-Dist: pendulum (==2.0.3)
Requires-Dist: click
Requires-Dist: lxml
Provides-Extra: docs
Requires-Dist: sphinx ; extra == 'docs'
Requires-Dist: sphinx-rtd-theme ; extra == 'docs'
Provides-Extra: tests
Requires-Dist: httmock ; extra == 'tests'
Requires-Dist: mock ; extra == 'tests'
Requires-Dist: pytest ; extra == 'tests'
Requires-Dist: coverage ; extra == 'tests'
